homebridge/__init__.py
pyhomebridge-0.0.3.dist-info/LICENSE
pyhomebridge-0.0.3.dist-info/METADATA
pyhomebridge-0.0.3.dist-info/WHEEL
pyhomebridge-0.0.3.dist-info/top_level.txt
pyhomebridge-0.0.3.dist-info/RECORD
