Metadata-Version: 2.1
Name: pyhomebridge
Version: 0.0.3
Summary: Control a homebridge server
Home-page: https://github.com/mroelandts/pyhomebridge
Author: mroelandts
Author-email: matthias_10@hotmail.com
License: MIT
Keywords: HomeBridge,HomeKit
Platform: UNKNOWN
Classifier: Development Status :: 3 - Alpha
Classifier: Intended Audience :: Developers
Classifier: Topic :: Software Development :: Build Tools
Classifier: License :: OSI Approved :: MIT License
Classifier: Programming Language :: Python :: 3
Classifier: Programming Language :: Python :: 3.5
Classifier: Programming Language :: Python :: 3.6
Requires-Dist: requests
Requires-Dist: argparse
